MANIFEST.in
README.md
setup.cfg
setup.py
TransVar.egg-info/PKG-INFO
TransVar.egg-info/SOURCES.txt
TransVar.egg-info/dependency_links.txt
TransVar.egg-info/requires.txt
TransVar.egg-info/top_level.txt
bin/transvar
external/pytabix/bam_endian.h
external/pytabix/bgzf.c
external/pytabix/bgzf.h
external/pytabix/bgzip.c
external/pytabix/index.c
external/pytabix/khash.h
external/pytabix/knetfile.c
external/pytabix/knetfile.h
external/pytabix/ksort.h
external/pytabix/kstring.c
external/pytabix/kstring.h
external/pytabix/tabix.h
external/pytabix/tabixmodule.c
external/ssw/encode.c
external/ssw/encode.h
external/ssw/ssw.c
external/ssw/ssw.h
test/test.py
transvar/__init__.py
transvar/anno.py
transvar/annodb.py
transvar/argparse.py
transvar/codonsearch.py
transvar/config.py
transvar/deletion.py
transvar/describe.py
transvar/err.py
transvar/faidx.py
transvar/frameshift.py
transvar/insertion.py
transvar/localdb.py
transvar/mnv.py
transvar/mutation.py
transvar/parser.py
transvar/proteinseqs.py
transvar/record.py
transvar/region.py
transvar/snv.py
transvar/transcripts.py
transvar/utils.py
transvar/version.py
transvar/ssw/__init__.py