Metadata-Version: 1.1
Name: TransVar
Version: 2.5.2.20190401
Summary: Transcript-based Variant annotator
Home-page: https://github.com/zwdzwd/transvar
Author: Wanding Zhou
Author-email: zhouwanding@gmail.com
License: MIT
Download-URL: https://github.com/zwdzwd/transvar/releases/latest
Keywords: bioinformatics,genomics
Platform: Linux
Platform: OSX
Classifier: Programming Language :: Python
Classifier: Development Status :: 6 - Mature
Classifier: Intended Audience :: Developers
Classifier: Intended Audience :: Science/Research
Classifier: License :: OSI Approved :: MIT License
Classifier: Operating System :: OS Independent
Classifier: Operating System :: POSIX
Classifier: Programming Language :: C
Classifier: Topic :: Scientific/Engineering :: Bio-Informatics
